EJERCICIO 4/ejercicio4.v
module gateLevel1(input wire A, B, C, output wire Y);

  wire n1, n2, n3, a1, a2, a3;

  not (n1, A);
  not (n2, B);
  not (n3, C);
  and (a1, n1, n3);
  and (a2, A, C);
  and (a3, A, n2);
  or  (Y, a1, a2, a3);

endmodule

module gateLevel2(input wire A, B, C, output wire Y);

  wire n1, n2, n3, a1, a2, a3;
  not (n2, B);
  or  (Y, n2);

endmodule

module gateLevel3(input wire A, B, C, D, output wire Y);

  wire n1, n2, n3, n4, a1, a2, a3, a4, a5, a6, a7, a8;
  not (n1, A);
  not (n2, B);
  not (n3, C);
  not (n4, D);
  and (a1, n1, n2, n3, n4);
  and (a2, n1, n2, C, D);
  and (a3, n1, B, n3, D);
  and (a4, n1, B, C, n4);
  and (a5, A, B, n3, n4);
  and (a6, A, B, C, D);
  and (a7, A, n2, n3, D);
  and (a8, A, n2, C, n4);
  or  (Y, a1, a2, a3, a4, a5, a6, a7, a8);

endmodule


module gateLevel4(input wire A, B, C, D, output wire Y);

  wire n1, a1, a2, a3;
  not (n1, D);
  and (a1, B, D);
  and (a2, A, n1);
  and (a3, A, C);
  or  (Y, a1, a2, a3);

endmodule

module operator1(input wire A, B, C, D, output wire Y);

  assign Y = (~B & ~C & ~D)|(A & ~C)|(A & ~B)|(A & ~D);

endmodule


module operator2(input wire A, B, C, output wire Y);

  assign Y = (~B|A|C);

endmodule

module operator3(input wire A, B, C, D, output wire Y);

  assign Y = (~C & D)| B | (A & D);

endmodule

module operator4(input wire A, B, C, output wire Y);

  assign Y = (~A&~C) | B;

endmodule

EJERCICIO 4/ejercicio4_tb.v
module testbench();

  reg a1, b1, c1, a2, b2, c2, a3, b3, c3, d3, a4, b4, c4, d4, a5, b5, c5, d5, a6, b6, c6, a7, b7, c7, d7, a8, b8, c8;
  wire Y1, Y2, Y3, Y4, Y5, Y6, Y7, Y8;

  gateLevel1   G1(a1, b1, c1, Y1);
  gateLevel2   G2(a2, b2, c2, Y2);
  gateLevel3   G3(a3, b3, c3, d3, Y3);
  gateLevel4   G4(a4, b4, c4, d4, Y4);
  operator1    O1(a5, b5, c5, d5, Y5);
  operator2    O2(a6, b6, c6, Y6);
  operator3    O3(a7, b7, c7, d7, Y7);
  operator4    O4(a8, b8, c8, Y8);

//Ejercicio 1 Tabla 1
  initial begin
    $display("Ejercicio 1 Tabla 1");
    $display("A B C | Y1");
    $display("------|---");
    $monitor("%b %b %b | %b", a1, b1, c1, Y1);
       a1 = 0; b1 = 0; c1 = 0;
    #1 a1 = 0; b1 = 0; c1 = 1;
    #1 a1 = 0; b1 = 1; c1 = 0;
    #1 a1 = 0; b1 = 1; c1 = 1;
    #1 a1 = 1; b1 = 0; c1 = 0;
    #1 a1 = 1; b1 = 0; c1 = 1;
    #1 a1 = 1; b1 = 1; c1 = 0;
    #1 a1 = 1; b1 = 1; c1 = 1;
  end

//Ejercicio 1 Tabla 2
  initial begin
    #8
    $display("");
    $display("Ejercicio 1 Tabla 2");
    $display("A B C | Y2");
    $display("------|------");
    $monitor("%b %b %b | %b", a2, b2, c2, Y2);
       a2 = 0; b2 = 0; c2 = 0;
    #1 a2 = 0; b2 = 0; c2 = 1;
    #1 a2 = 0; b2 = 1; c2 = 0;
    #1 a2 = 0; b2 = 1; c2 = 1;
    #1 a2 = 1; b2 = 0; c2 = 0;
    #1 a2 = 1; b2 = 0; c2 = 1;
    #1 a2 = 1; b2 = 1; c2 = 0;
    #1 a2 = 1; b2 = 1; c2 = 1;
  end

  //Ejercicio 1 Tabla 3
    initial begin
      #16
      $display("");
      $display("Ejercicio 1 Tabla 3");
      $display("A B C D | Y3");
      $display("--------|---");
      $monitor("%b %b %b %b | %b", a3, b3, c3, d3, Y3);
         a3 = 0; b3 = 0; c3 = 0; d3 = 0;
      #1 a3 = 0; b3 = 0; c3 = 0; d3 = 1;
      #1 a3 = 0; b3 = 0; c3 = 1; d3 = 0;
      #1 a3 = 0; b3 = 0; c3 = 1; d3 = 1;
      #1 a3 = 0; b3 = 1; c3 = 0; d3 = 0;
      #1 a3 = 0; b3 = 1; c3 = 0; d3 = 1;
      #1 a3 = 0; b3 = 1; c3 = 1; d3 = 0;
      #1 a3 = 0; b3 = 1; c3 = 1; d3 = 1;
      #1 a3 = 1; b3 = 0; c3 = 0; d3 = 0;
      #1 a3 = 1; b3 = 0; c3 = 0; d3 = 1;
      #1 a3 = 1; b3 = 0; c3 = 1; d3 = 0;
      #1 a3 = 1; b3 = 0; c3 = 1; d3 = 1;
      #1 a3 = 1; b3 = 1; c3 = 0; d3 = 0;
      #1 a3 = 1; b3 = 1; c3 = 0; d3 = 1;
      #1 a3 = 1; b3 = 1; c3 = 1; d3 = 0;
      #1 a3 = 1; b3 = 1; c3 = 1; d3 = 1;


    end

    //Ejercicio 1 Tabla 4
      initial begin
        #32
        $display("");
        $display("Ejercicio 1 Tabla 4");
        $display("A B C D | Y4");
        $display("--------|---");
        $monitor("%b %b %b %b | %b", a4, b4, c4, d4, Y4);
           a4 = 0; b4 = 0; c4 = 0; d4 = 0;
        #1 a4 = 0; b4 = 0; c4 = 0; d4 = 1;
        #1 a4 = 0; b4 = 0; c4 = 1; d4 = 0;
        #1 a4 = 0; b4 = 0; c4 = 1; d4 = 1;
        #1 a4 = 0; b4 = 1; c4 = 0; d4 = 0;
        #1 a4 = 0; b4 = 1; c4 = 0; d4 = 1;
        #1 a4 = 0; b4 = 1; c4 = 1; d4 = 0;
        #1 a4 = 0; b4 = 1; c4 = 1; d4 = 1;
        #1 a4 = 1; b4 = 0; c4 = 0; d4 = 0;
        #1 a4 = 1; b4 = 0; c4 = 0; d4 = 1;
        #1 a4 = 1; b4 = 0; c4 = 1; d4 = 0;
        #1 a4 = 1; b4 = 0; c4 = 1; d4 = 1;
        #1 a4 = 1; b4 = 1; c4 = 0; d4 = 0;
        #1 a4 = 1; b4 = 1; c4 = 0; d4 = 1;
        #1 a4 = 1; b4 = 1; c4 = 1; d4 = 0;
        #1 a4 = 1; b4 = 1; c4 = 1; d4 = 1;


      end

      //Ejercicio 2 Tabla 1
        initial begin
          #48
          $display("");
          $display("Ejercicio 2 Tabla 1");
          $display("A B C D | Y5");
          $display("--------|---");
          $monitor("%b %b %b %b | %b", a5, b5, c5, d5, Y5);
             a5 = 0; b5 = 0; c5 = 0; d5 = 0;
          #1 a5 = 0; b5 = 0; c5 = 0; d5 = 1;
          #1 a5 = 0; b5 = 0; c5 = 1; d5 = 0;
          #1 a5 = 0; b5 = 0; c5 = 1; d5 = 1;
          #1 a5 = 0; b5 = 1; c5 = 0; d5 = 0;
          #1 a5 = 0; b5 = 1; c5 = 0; d5 = 1;
          #1 a5 = 0; b5 = 1; c5 = 1; d5 = 0;
          #1 a5 = 0; b5 = 1; c5 = 1; d5 = 1;
          #1 a5 = 1; b5 = 0; c5 = 0; d5 = 0;
          #1 a5 = 1; b5 = 0; c5 = 0; d5 = 1;
          #1 a5 = 1; b5 = 0; c5 = 1; d5 = 0;
          #1 a5 = 1; b5 = 0; c5 = 1; d5 = 1;
          #1 a5 = 1; b5 = 1; c5 = 0; d5 = 0;
          #1 a5 = 1; b5 = 1; c5 = 0; d5 = 1;
          #1 a5 = 1; b5 = 1; c5 = 1; d5 = 0;
          #1 a5 = 1; b5 = 1; c5 = 1; d5 = 1;


        end

        //Ejercicio 2 Tabla 2
          initial begin
            #64
            $display("");
            $display("Ejercicio 2 Tabla 2");
            $display("A B C | Y6");
            $display("------|------");
            $monitor("%b %b %b | %b", a6, b6, c6, Y6);
               a6 = 0; b6 = 0; c6 = 0;
            #1 a6 = 0; b6 = 0; c6 = 1;
            #1 a6 = 0; b6 = 1; c6 = 0;
            #1 a6 = 0; b6 = 1; c6 = 1;
            #1 a6 = 1; b6 = 0; c6 = 0;
            #1 a6 = 1; b6 = 0; c6 = 1;
            #1 a6 = 1; b6 = 1; c6 = 0;
            #1 a6 = 1; b6 = 1; c6 = 1;
          end

          //Ejercicio 2 Tabla 3
            initial begin
              #72
              $display("");
              $display("Ejercicio 2 Tabla 3");
              $display("A B C D | Y7");
              $display("--------|---");
              $monitor("%b %b %b %b | %b", a7, b7, c7, d7, Y7);
                 a7 = 0; b7 = 0; c7 = 0; d7 = 0;
              #1 a7 = 0; b7 = 0; c7 = 0; d7 = 1;
              #1 a7 = 0; b7 = 0; c7 = 1; d7 = 0;
              #1 a7 = 0; b7 = 0; c7 = 1; d7 = 1;
              #1 a7 = 0; b7 = 1; c7 = 0; d7 = 0;
              #1 a7 = 0; b7 = 1; c7 = 0; d7 = 1;
              #1 a7 = 0; b7 = 1; c7 = 1; d7 = 0;
              #1 a7 = 0; b7 = 1; c7 = 1; d7 = 1;
              #1 a7 = 1; b7 = 0; c7 = 0; d7 = 0;
              #1 a7 = 1; b7 = 0; c7 = 0; d7 = 1;
              #1 a7 = 1; b7 = 0; c7 = 1; d7 = 0;
              #1 a7 = 1; b7 = 0; c7 = 1; d7 = 1;
              #1 a7 = 1; b7 = 1; c7 = 0; d7 = 0;
              #1 a7 = 1; b7 = 1; c7 = 0; d7 = 1;
              #1 a7 = 1; b7 = 1; c7 = 1; d7 = 0;
              #1 a7 = 1; b7 = 1; c7 = 1; d7 = 1;


            end

            //Ejercicio 2 Tabla 4
              initial begin
                #80
                $display("");
                $display("Ejercicio 2 Tabla 4");
                $display("A B C | Y8");
                $display("------|------");
                $monitor("%b %b %b | %b", a8, b8, c8, Y8);
                   a8 = 0; b8 = 0; c8 = 0;
                #1 a8 = 0; b8 = 0; c8 = 1;
                #1 a8 = 0; b8 = 1; c8 = 0;
                #1 a8 = 0; b8 = 1; c8 = 1;
                #1 a8 = 1; b8 = 0; c8 = 0;
                #1 a8 = 1; b8 = 0; c8 = 1;
                #1 a8 = 1; b8 = 1; c8 = 0;
                #1 a8 = 1; b8 = 1; c8 = 1;
              end

  initial
    #97 $finish;

  initial begin
    $dumpfile("ejercicio4_tb.vcd");
    $dumpvars(0, testbench);
  end

endmodule

EJERCICIO 4/ejercicio4_tb.vcd
$date
	Sun Aug 09 22:31:20 2020
$end
$version
	Icarus Verilog
$end
$timescale
	1ps
$end
$scope module testbench $end
$var wire 1 ! Y8 $end
$var wire 1 " Y7 $end
$var wire 1 # Y6 $end
$var wire 1 $ Y5 $end
$var wire 1 % Y4 $end
$var wire 1 & Y3 $end
$var wire 1 ' Y2 $end
$var wire 1 ( Y1 $end
$var reg 1 ) a1 $end
$var reg 1 * a2 $end
$var reg 1 + a3 $end
$var reg 1 , a4 $end
$var reg 1 - a5 $end
$var reg 1 . a6 $end
$var reg 1 / a7 $end
$var reg 1 0 a8 $end
$var reg 1 1 b1 $end
$var reg 1 2 b2 $end
$var reg 1 3 b3 $end
$var reg 1 4 b4 $end
$var reg 1 5 b5 $end
$var reg 1 6 b6 $end
$var reg 1 7 b7 $end
$var reg 1 8 b8 $end
$var reg 1 9 c1 $end
$var reg 1 : c2 $end
$var reg 1 ; c3 $end
$var reg 1 < c4 $end
$var reg 1 = c5 $end
$var reg 1 > c6 $end
$var reg 1 ? c7 $end
$var reg 1 @ c8 $end
$var reg 1 A d3 $end
$var reg 1 B d4 $end
$var reg 1 C d5 $end
$var reg 1 D d7 $end
$scope module G1 $end
$var wire 1 ) A $end
$var wire 1 1 B $end
$var wire 1 9 C $end
$var wire 1 ( Y $end
$var wire 1 E a1 $end
$var wire 1 F a2 $end
$var wire 1 G a3 $end
$var wire 1 H n1 $end
$var wire 1 I n2 $end
$var wire 1 J n3 $end
$upscope $end
$scope module G2 $end
$var wire 1 * A $end
$var wire 1 2 B $end
$var wire 1 : C $end
$var wire 1 ' Y $end
$var wire 1 K n2 $end
$upscope $end
$scope module G3 $end
$var wire 1 + A $end
$var wire 1 3 B $end
$var wire 1 ; C $end
$var wire 1 A D $end
$var wire 1 & Y $end
$var wire 1 L a1 $end
$var wire 1 M a2 $end
$var wire 1 N a3 $end
$var wire 1 O a4 $end
$var wire 1 P a5 $end
$var wire 1 Q a6 $end
$var wire 1 R a7 $end
$var wire 1 S a8 $end
$var wire 1 T n1 $end
$var wire 1 U n2 $end
$var wire 1 V n3 $end
$var wire 1 W n4 $end
$upscope $end
$scope module G4 $end
$var wire 1 , A $end
$var wire 1 4 B $end
$var wire 1 < C $end
$var wire 1 B D $end
$var wire 1 % Y $end
$var wire 1 X a1 $end
$var wire 1 Y a2 $end
$var wire 1 Z a3 $end
$var wire 1 [ n1 $end
$upscope $end
$scope module O1 $end
$var wire 1 - A $end
$var wire 1 5 B $end
$var wire 1 = C $end
$var wire 1 C D $end
$var wire 1 $ Y $end
$upscope $end
$scope module O2 $end
$var wire 1 . A $end
$var wire 1 6 B $end
$var wire 1 > C $end
$var wire 1 # Y $end
$upscope $end
$scope module O3 $end
$var wire 1 / A $end
$var wire 1 7 B $end
$var wire 1 ? C $end
$var wire 1 D D $end
$var wire 1 " Y $end
$upscope $end
$scope module O4 $end
$var wire 1 0 A $end
$var wire 1 8 B $end
$var wire 1 @ C $end
$var wire 1 ! Y $end
$upscope $end
$upscope $end
$enddefinitions $end
#0
$dumpvars
x[
xZ
xY
xX
xW
xV
xU
xT
xS
xR
xQ
xP
xO
xN
xM
xL
xK
1J
1I
1H
0G
0F
1E
xD
xC
xB
xA
x@
x?
x>
x=
x<
x;
x:
09
x8
x7
x6
x5
x4
x3
x2
01
x0
x/
x.
x-
x,
x+
x*
0)
1(
x'
x&
x%
x$
x#
x"
x!
$end
#1
0(
0E
0J
19
#2
1(
1E
1J
0I
09
11
#3
0(
0E
0J
19
#4
1(
1G
1J
1I
0H
09
01
1)
#5
0J
1F
19
#6
0(
0G
1J
0F
0I
09
11
#7
1(
0J
1F
19
#8
1'
1K
0:
02
0*
#9
1:
#10
0'
0K
0:
12
#11
1:
#12
1'
1K
0:
02
1*
#13
1:
#14
0'
0K
0:
12
#15
1:
#16
1&
1L
1W
1V
0M
1U
0N
0O
1T
0P
0Q
0R
0S
0A
0;
03
0+
#17
0&
0L
0W
1A
#18
1W
0V
0A
1;
#19
1&
0W
1M
1A
#20
0&
1W
1V
0M
0U
0A
0;
13
#21
1&
0W
1N
1A
#22
1&
1O
1W
0N
0V
0A
1;
#23
0&
0O
0W
1A
#24
1W
1V
1U
0T
0A
0;
03
1+
#25
1&
0W
1R
1A
#26
1&
1S
1W
0R
0V
0A
1;
#27
0&
0S
0W
1A
#28
1&
1P
1W
1V
0U
0A
0;
13
#29
0&
0P
0W
1A
#30
1W
0V
0A
1;
#31
1&
0W
1Q
1A
#32
0%
1[
0X
0Y
0Z
0B
0<
04
0,
#33
0[
1B
#34
1[
0B
1<
#35
0[
1B
#36
1[
0B
0<
14
#37
1%
0[
1X
1B
#38
0%
1[
0X
0B
1<
#39
1%
0[
1X
1B
#40
1Y
1%
1[
0X
0B
0<
04
1,
#41
0%
0Y
0[
1B
#42
1Y
1%
1[
1Z
0B
1<
#43
0Y
0[
1B
#44
1Y
1%
1[
0Z
0B
0<
14
#45
0Y
0[
1X
1B
#46
1Y
1[
0X
1Z
0B
1<
#47
0Y
0[
1X
1B
#48
1$
0C
0=
05
0-
#49
0$
1C
#50
0C
1=
#51
1C
#52
0C
0=
15
#53
1C
#54
0C
1=
#55
1C
#56
1$
0C
0=
05
1-
#57
1C
#58
0C
1=
#59
1C
#60
0C
0=
15
#61
1C
#62
0C
1=
#63
0$
1C
#64
1#
0>
06
0.
#65
1>
#66
0#
0>
16
#67
1#
1>
#68
0>
06
1.
#69
1>
#70
0>
16
#71
1>
#72
0"
0D
0?
07
0/
#73
1"
1D
#74
0"
0D
1?
#75
1D
#76
1"
0D
0?
17
#77
1D
#78
0D
1?
#79
1D
#80
1!
0"
0D
0?
07
1/
0@
08
00
#81
0!
1"
1D
1@
#82
0"
1!
0D
1?
0@
18
#83
1"
1D
1@
#84
0!
0D
0?
17
0@
08
10
#85
1D
1@
#86
1!
0D
1?
0@
18
#87
1D
1@
