EJERCICIO 5/ejercicio5.v
module gateLevel1(input wire A, B, C, output wire Y);

  wire n1, n2, n3, a1, a2, a3;

  not (n1, A);
  not (n2, B);
  not (n3, C);
  and (a1, A, n2, n3);
  and (a2, A, n2, C);
  and (a3, A, B, C);
  or  (Y, a1, a2, a3);

endmodule

module operator1(input wire A, B, C, output wire Y);

  assign Y = (A&~B&~C)|(A&~B&C)|(A&B&C);

endmodule

module gateLevel2(input wire A, B, C, output wire Y);

  wire n1, n2, n3, a1, a2, a3, a4, a5;

  not (n1, A);
  not (n2, B);
  not (n3, C);
  or (a1, A, B, B);
  or (a2, A, B, n3);
  or (a3, A, n2, C);
  or (a4, A, n2, n3);
  or (a5, n1, n2, C);
  and (Y, a1, a2, a3, a4, a5);

endmodule

module operator2(input wire A, B, C, output wire Y);

  assign Y = (A|B|C)&(A|B|~C)&(A|~B|C)&(A|~B|~C)&(~A|~B|C) ;

endmodule

module gateLevel3(input wire A, B, C, output wire Y);

  wire n1, n2, n3, a1, a2;

  not (n2, B);
  and (a1, A, n2);
  and (a2, A, C);
  or  (Y, a1, a2);

endmodule

module operator3(input wire A, B, C, output wire Y);

  assign Y = (A&~B)|(A&C) ;

endmodule

EJERCICIO 5/ejercicio5_tb.v
module testbench();

  reg a1, b1, c1, a2, b2, c2, a3, b3, c3, a4, b4, c4, a5, b5, c5, a6, b6, c6;
  wire Y1, Y2, Y3, Y4, Y5, Y6;

  gateLevel1   G1(a1, b1, c1, Y1);
  operator1   O1(a2, b2, c2, Y2);
  gateLevel2 G2(a3, b3, c3 , Y3);
  operator2   O2(a4, b4, c4, Y4);
  gateLevel3 G3(a5, b5, c5 , Y5);
  operator3   O3(a6, b6, c6, Y6);




  //Ejercicio 5 SOP gateleveling modelling
    initial begin
      $display("Ejercicio 5 SOP GATE LEVEL MODELLING");
      $display("A B C | Y1");
      $display("------|---");
      $monitor("%b %b %b | %b", a1, b1, c1, Y1);
         a1 = 0; b1 = 0; c1 = 0;
      #1 a1 = 0; b1 = 0; c1 = 1;
      #1 a1 = 0; b1 = 1; c1 = 0;
      #1 a1 = 0; b1 = 1; c1 = 1;
      #1 a1 = 1; b1 = 0; c1 = 0;
      #1 a1 = 1; b1 = 0; c1 = 1;
      #1 a1 = 1; b1 = 1; c1 = 0;
      #1 a1 = 1; b1 = 1; c1 = 1;
    end

    //Ejercicio 5 SOP BEHAVIOUR MODELLING
      initial begin
        #8
        $display("");
        $display("Ejercicio 5 SOP BEHAVIOUR MODELLING ");
        $display("A B C | Y2");
        $display("------|------");
        $monitor("%b %b %b | %b", a2, b2, c2, Y2);
           a2 = 0; b2 = 0; c2 = 0;
        #1 a2 = 0; b2 = 0; c2 = 1;
        #1 a2 = 0; b2 = 1; c2 = 0;
        #1 a2 = 0; b2 = 1; c2 = 1;
        #1 a2 = 1; b2 = 0; c2 = 0;
        #1 a2 = 1; b2 = 0; c2 = 1;
        #1 a2 = 1; b2 = 1; c2 = 0;
        #1 a2 = 1; b2 = 1; c2 = 1;
      end

      //Ejercicio 5 POS gateleveling modelling
        initial begin
          #16
          $display("Ejercicio 5 POS GATE LEVEL MODELLING");
          $display("A B C | Y3");
          $display("------|---");
          $monitor("%b %b %b | %b", a3, b3, c3, Y3);
             a3 = 0; b3 = 0; c3 = 0;
          #1 a3 = 0; b3 = 0; c3 = 1;
          #1 a3 = 0; b3 = 1; c3 = 0;
          #1 a3 = 0; b3 = 1; c3 = 1;
          #1 a3 = 1; b3 = 0; c3 = 0;
          #1 a3 = 1; b3 = 0; c3 = 1;
          #1 a3 = 1; b3 = 1; c3 = 0;
          #1 a3 = 1; b3 = 1; c3 = 1;
        end

        //Ejercicio 5 POS BEHAVIOUR MODELLING
          initial begin
            #24
            $display("");
            $display("Ejercicio 5 POS BEHAVIOUR MODELLING ");
            $display("A B C | Y4");
            $display("------|------");
            $monitor("%b %b %b | %b", a4, b4, c4, Y4);
               a4 = 0; b4 = 0; c4 = 0;
            #1 a4 = 0; b4 = 0; c4 = 1;
            #1 a4 = 0; b4 = 1; c4 = 0;
            #1 a4 = 0; b4 = 1; c4 = 1;
            #1 a4 = 1; b4 = 0; c4 = 0;
            #1 a4 = 1; b4 = 0; c4 = 1;
            #1 a4 = 1; b4 = 1; c4 = 0;
            #1 a4 = 1; b4 = 1; c4 = 1;
          end




    //Ejercicio 5 MAP KARNAUGH gateleveling modelling
      initial begin
        #32
        $display("Ejercicio 5 MAP KARNAUGH GATE LEVEL MODELLING");
        $display("A B C | Y5");
        $display("------|---");
        $monitor("%b %b %b | %b", a5, b5, c5, Y5);
           a5 = 0; b5 = 0; c5 = 0;
        #1 a5 = 0; b5 = 0; c5 = 1;
        #1 a5 = 0; b5 = 1; c5 = 0;
        #1 a5 = 0; b5 = 1; c5 = 1;
        #1 a5 = 1; b5 = 0; c5 = 0;
        #1 a5 = 1; b5 = 0; c5 = 1;
        #1 a5 = 1; b5 = 1; c5 = 0;
        #1 a5 = 1; b5 = 1; c5 = 1;
      end

      //Ejercicio 5 MAP KARNAUGH BEHAVIOUR MODELLING
        initial begin
          #40
          $display("");
          $display("Ejercicio 5 MAP KARNAUGH BEHAVIOUR MODELLING ");
          $display("A B C | Y6");
          $display("------|------");
          $monitor("%b %b %b | %b", a6, b6, c6, Y6);
             a6 = 0; b6 = 0; c6 = 0;
          #1 a6 = 0; b6 = 0; c6 = 1;
          #1 a6 = 0; b6 = 1; c6 = 0;
          #1 a6 = 0; b6 = 1; c6 = 1;
          #1 a6 = 1; b6 = 0; c6 = 0;
          #1 a6 = 1; b6 = 0; c6 = 1;
          #1 a6 = 1; b6 = 1; c6 = 0;
          #1 a6 = 1; b6 = 1; c6 = 1;
        end

      initial
      #97 $finish;

    initial begin
      $dumpfile("ejercicio5_tb.vcd");
      $dumpvars(0, testbench);
    end

endmodule

EJERCICIO 5/ejercicio5_tb.vcd
$date
	Sun Aug 09 23:05:44 2020
$end
$version
	Icarus Verilog
$end
$timescale
	1ps
$end
$scope module testbench $end
$var wire 1 ! Y6 $end
$var wire 1 " Y5 $end
$var wire 1 # Y4 $end
$var wire 1 $ Y3 $end
$var wire 1 % Y2 $end
$var wire 1 & Y1 $end
$var reg 1 ' a1 $end
$var reg 1 ( a2 $end
$var reg 1 ) a3 $end
$var reg 1 * a4 $end
$var reg 1 + a5 $end
$var reg 1 , a6 $end
$var reg 1 - b1 $end
$var reg 1 . b2 $end
$var reg 1 / b3 $end
$var reg 1 0 b4 $end
$var reg 1 1 b5 $end
$var reg 1 2 b6 $end
$var reg 1 3 c1 $end
$var reg 1 4 c2 $end
$var reg 1 5 c3 $end
$var reg 1 6 c4 $end
$var reg 1 7 c5 $end
$var reg 1 8 c6 $end
$scope module G1 $end
$var wire 1 ' A $end
$var wire 1 - B $end
$var wire 1 3 C $end
$var wire 1 & Y $end
$var wire 1 9 a1 $end
$var wire 1 : a2 $end
$var wire 1 ; a3 $end
$var wire 1 < n1 $end
$var wire 1 = n2 $end
$var wire 1 > n3 $end
$upscope $end
$scope module G2 $end
$var wire 1 ) A $end
$var wire 1 / B $end
$var wire 1 5 C $end
$var wire 1 $ Y $end
$var wire 1 ? a1 $end
$var wire 1 @ a2 $end
$var wire 1 A a3 $end
$var wire 1 B a4 $end
$var wire 1 C a5 $end
$var wire 1 D n1 $end
$var wire 1 E n2 $end
$var wire 1 F n3 $end
$upscope $end
$scope module G3 $end
$var wire 1 + A $end
$var wire 1 1 B $end
$var wire 1 7 C $end
$var wire 1 " Y $end
$var wire 1 G a1 $end
$var wire 1 H a2 $end
$var wire 1 I n2 $end
$upscope $end
$scope module O1 $end
$var wire 1 ( A $end
$var wire 1 . B $end
$var wire 1 4 C $end
$var wire 1 % Y $end
$upscope $end
$scope module O2 $end
$var wire 1 * A $end
$var wire 1 0 B $end
$var wire 1 6 C $end
$var wire 1 # Y $end
$upscope $end
$scope module O3 $end
$var wire 1 , A $end
$var wire 1 2 B $end
$var wire 1 8 C $end
$var wire 1 ! Y $end
$upscope $end
$upscope $end
$enddefinitions $end
#0
$dumpvars
xI
xH
xG
xF
xE
xD
xC
xB
xA
x@
x?
1>
1=
1<
0;
0:
09
x8
x7
x6
x5
x4
03
x2
x1
x0
x/
x.
0-
x,
x+
x*
x)
x(
0'
0&
x%
x$
x#
x"
x!
$end
#1
0>
13
#2
1>
0=
03
1-
#3
0>
13
#4
1&
19
1>
1=
0<
03
0-
1'
#5
09
0>
1:
13
#6
0&
1>
0:
0=
03
1-
#7
1&
0>
1;
13
#8
0%
04
0.
0(
#9
14
#10
04
1.
#11
14
#12
1%
04
0.
1(
#13
14
#14
0%
04
1.
#15
1%
14
#16
0$
1@
1A
1B
1F
1C
1E
1D
0?
05
0/
0)
#17
0@
0F
15
#18
1F
0A
0E
1?
1@
05
1/
#19
0$
0B
0F
1A
15
#20
1$
1F
1E
0D
1B
05
0/
1)
#21
0F
15
#22
0$
1F
0C
0E
05
1/
#23
1$
0F
1C
15
#24
0#
06
00
0*
#25
16
#26
06
10
#27
16
#28
1#
06
00
1*
#29
16
#30
0#
06
10
#31
1#
16
#32
0"
1I
0G
0H
07
01
0+
#33
17
#34
0I
07
11
#35
17
#36
1"
1G
1I
07
01
1+
#37
1H
17
#38
0"
0G
0H
0I
07
11
#39
1"
1H
17
#40
0!
08
02
0,
#41
18
#42
08
12
#43
18
#44
1!
08
02
1,
#45
18
#46
0!
08
12
#47
1!
18
